vsgrlir/__init__.py
vsgrlir/__main__.py
vsgrlir/grl.py
vsgrlir/mixed_attn_block.py
vsgrlir/mixed_attn_block_efficient.py
vsgrlir/ops.py
vsgrlir/swin_v1_block.py
vsgrlir/upsample.py
vsgrlir/models/bsr_grl_base.ckpt
vsgrlir/models/db_defocus_single_pixel_grl_base.ckpt
vsgrlir/models/db_motion_grl_base_gopro.ckpt
vsgrlir/models/db_motion_grl_base_realblur_j.ckpt
vsgrlir/models/db_motion_grl_base_realblur_r.ckpt
vsgrlir/models/dm_grl_small.ckpt
vsgrlir/models/dn_grl_small_c3s15.ckpt
vsgrlir/models/dn_grl_small_c3s25.ckpt
vsgrlir/models/dn_grl_small_c3s50.ckpt
vsgrlir/models/jpeg_grl_small_c3q10.ckpt
vsgrlir/models/jpeg_grl_small_c3q20.ckpt
vsgrlir/models/jpeg_grl_small_c3q30.ckpt
vsgrlir/models/jpeg_grl_small_c3q40.ckpt
vsgrlir/models/sr_grl_small_c3x2.ckpt
vsgrlir/models/sr_grl_small_c3x3.ckpt
vsgrlir/models/sr_grl_small_c3x4.ckpt
vsgrlir-1.1.1.dist-info/METADATA
vsgrlir-1.1.1.dist-info/WHEEL
vsgrlir-1.1.1.dist-info/licenses/LICENSE
vsgrlir-1.1.1.dist-info/RECORD
