Metadata-Version: 2.1
Name: vsgrlir
Version: 1.1.1
Summary: GRLIR function for VapourSynth
Project-URL: Homepage, https://github.com/HolyWu/vs-grlir
Project-URL: Bug Tracker, https://github.com/HolyWu/vs-grlir/issues
Author-email: HolyWu <holywu@gmail.com>
License: MIT License
License-File: LICENSE
Keywords: GRLIR,VapourSynth
Classifier: License :: OSI Approved :: MIT License
Classifier: Operating System :: OS Independent
Classifier: Programming Language :: Python :: 3.10
Classifier: Topic :: Multimedia :: Video
Requires-Python: >=3.10
Requires-Dist: numpy>=1.24.2
Requires-Dist: omegaconf>=2.3.0
Requires-Dist: requests>=2.28.2
Requires-Dist: timm>=0.6.13
Requires-Dist: torch>=1.13.1
Requires-Dist: tqdm>=4.65.0
Requires-Dist: vapoursynth>=55
Requires-Dist: vsutil>=0.8.0
